jobdispatcher/__init__.py
jobdispatcher/engines.py
jobdispatcher/index_based_loops.py
jobdispatcher/job_balancers.py
jobdispatcher/jobs.py
jobdispatcher/processor.py
jobdispatcher/packing/__init__.py
jobdispatcher/packing/chunker.py
jobdispatcher/packing/to_constant_volume.py
jobdispatcher-0.2.0.dist-info/LICENSE
jobdispatcher-0.2.0.dist-info/METADATA
jobdispatcher-0.2.0.dist-info/WHEEL
jobdispatcher-0.2.0.dist-info/top_level.txt
jobdispatcher-0.2.0.dist-info/RECORD
