Metadata-Version: 2.1
Name: jobdispatcher
Version: 0.2.0
Summary: A simplified python interface for running embarassingly parallel calculations.
Home-page: https://github.com/mattiafelice-palermo/job-dispatcher
Author: Mattia Felice Palermo
Author-email: Mattia Felice Palermo <mpalermo@gmail.com>
License: GNU GENERAL PUBLIC LICENSE
Classifier: Development Status :: 5 - Production/Stable
Classifier: Intended Audience :: Developers
Classifier: Intended Audience :: Science/Research
Classifier: License :: OSI Approved :: GNU General Public License v3 (GPLv3)
Classifier: Programming Language :: Python
Classifier: Programming Language :: Python :: 3
Classifier: Topic :: Software Development :: Libraries :: Python Modules
Classifier: Topic :: Scientific/Engineering
Requires-Python: >=3.8
License-File: LICENSE
Provides-Extra: testing
Requires-Dist: pytest >=6.0 ; extra == 'testing'
Requires-Dist: pytest-cov >=2.0 ; extra == 'testing'
Requires-Dist: mypy >=0.910 ; extra == 'testing'
Requires-Dist: flake8 >=3.9 ; extra == 'testing'
Requires-Dist: tox >=3.24 ; extra == 'testing'
Requires-Dist: numpy ; extra == 'testing'
